{
  "name": "Thundering Spirit",
  "icon": "asuna:thundering_spirit",
  "category": "getting_started",
  "sortnum": 7,
  "pages": [
    {
      "type": "text",
      "text": "You notice that ender pearls are able to store up high amounts of mana and brainstorm of a way to infuse mana into them by infusing elements along with it."
    },
    {
      "type": "altar_recipe",
      "required_mana": 64,
      "center": "minecraft:ender_pearl",
      "item_groups": {
        "First Ring": [
          "asuna:mana_shard",
          "asuna:mana_shard",
          "asuna:mana_shard",
          "asuna:mana_shard"
        ],
        "Second Ring": [
          "minecraft:iron_bars",
          "minecraft:iron_ingot",
          "minecraft:iron_block",
          "minecraft:iron_nugget"
        ]
      }
    }
  ]
}